[{"rating": 4.3, "name": "The Shops at Columbus Circle", "geometry": {"location": {"lat": 40.7686013, "lng": -73.98321159999999}, "viewport": {"northeast": {"lat": 40.7696206302915, "lng": -73.9813545697085}, "southwest": {"lat": 40.7669226697085, "lng": -73.9840525302915}}}, "opening_hours": {"weekday_text": ["Monday: 10:00 AM \u2013 9:00 PM", "Tuesday: 10:00 AM \u2013 9:00 PM", "Wednesday: 10:00 AM \u2013 9:00 PM", "Thursday: 10:00 AM \u2013 9:00 PM", "Friday: 10:00 AM \u2013 9:00 PM", "Saturday: 10:00 AM \u2013 9:00 PM", "Sunday: 11:00 AM \u2013 7:00 PM"], "open_now": false, "periods": [{"close": {"day": 0, "time": "1900"}, "open": {"day": 0, "time": "1100"}}, {"close": {"day": 1, "time": "2100"}, "open": {"day": 1, "time": "1000"}}, {"close": {"day": 2, "time": "2100"}, "open": {"day": 2, "time": "1000"}}, {"close": {"day": 3, "time": "2100"}, "open": {"day": 3, "time": "1000"}}, {"close": {"day": 4, "time": "2100"}, "open": {"day": 4, "time": "1000"}}, {"close": {"day": 5, "time": "2100"}, "open": {"day": 5, "time": "1000"}}, {"close": {"day": 6, "time": "2100"}, "open": {"day": 6, "time": "1000"}}]}, "place_id": "ChIJp3PsL_ZYwokRdBcE-3KTjrg", "formatted_phone_number": "(212) 823-6300", "formatted_address": "10 Columbus Cir, New York, NY 10019, USA"}, {"rating": 5, "name": "Shopping Girlfriend NYC", "geometry": {"location": {"lat": 40.7559712, "lng": -73.99204519999999}, "viewport": {"northeast": {"lat": 40.7572140302915, "lng": -73.99077376970848}, "southwest": {"lat": 40.7545160697085, "lng": -73.9934717302915}}}, "place_id": "ChIJUdrSNb5ZwokRsoOdOHCNBQk", "formatted_phone_number": "(917) 825-2564", "formatted_address": "315 W 39th St, New York, NY 10018, USA"}, {"rating": 3.9, "name": "Manhattan Mall", "geometry": {"location": {"lat": 40.74926629999999, "lng": -73.9893112}, "viewport": {"northeast": {"lat": 40.7504378802915, "lng": -73.98773971970849}, "southwest": {"lat": 40.7477399197085, "lng": -73.9904376802915}}}, "opening_hours": {"weekday_text": ["Monday: 9:00 AM \u2013 9:30 PM", "Tuesday: 9:00 AM \u2013 9:30 PM", "Wednesday: 9:00 AM \u2013 9:30 PM", "Thursday: 9:00 AM \u2013 9:30 PM", "Friday: 9:00 AM \u2013 9:30 PM", "Saturday: 9:00 AM \u2013 9:30 PM", "Sunday: 10:00 AM \u2013 8:30 PM"], "open_now": false, "periods": [{"close": {"day": 0, "time": "2030"}, "open": {"day": 0, "time": "1000"}}, {"close": {"day": 1, "time": "2130"}, "open": {"day": 1, "time": "0900"}}, {"close": {"day": 2, "time": "2130"}, "open": {"day": 2, "time": "0900"}}, {"close": {"day": 3, "time": "2130"}, "open": {"day": 3, "time": "0900"}}, {"close": {"day": 4, "time": "2130"}, "open": {"day": 4, "time": "0900"}}, {"close": {"day": 5, "time": "2130"}, "open": {"day": 5, "time": "0900"}}, {"close": {"day": 6, "time": "2130"}, "open": {"day": 6, "time": "0900"}}]}, "place_id": "ChIJ6-70LKlZwokRzdXlGpoA_so", "formatted_phone_number": "(212) 465-0500", "formatted_address": "100 West 33rd Street, New York, NY 10001, USA"}, {"rating": 4.6, "name": "Westfield World Trade Center", "geometry": {"location": {"lat": 40.7114771, "lng": -74.011478}, "viewport": {"northeast": {"lat": 40.71282608029151, "lng": -74.01012901970849}, "southwest": {"lat": 40.71012811970851, "lng": -74.01282698029149}}}, "opening_hours": {"weekday_text": ["Monday: 10:00 AM \u2013 9:00 PM", "Tuesday: 10:00 AM \u2013 9:00 PM", "Wednesday: 10:00 AM \u2013 9:00 PM", "Thursday: 10:00 AM \u2013 9:00 PM", "Friday: 10:00 AM \u2013 9:00 PM", "Saturday: 10:00 AM \u2013 9:00 PM", "Sunday: 11:00 AM \u2013 7:00 PM"], "open_now": false, "periods": [{"close": {"day": 0, "time": "1900"}, "open": {"day": 0, "time": "1100"}}, {"close": {"day": 1, "time": "2100"}, "open": {"day": 1, "time": "1000"}}, {"close": {"day": 2, "time": "2100"}, "open": {"day": 2, "time": "1000"}}, {"close": {"day": 3, "time": "2100"}, "open": {"day": 3, "time": "1000"}}, {"close": {"day": 4, "time": "2100"}, "open": {"day": 4, "time": "1000"}}, {"close": {"day": 5, "time": "2100"}, "open": {"day": 5, "time": "1000"}}, {"close": {"day": 6, "time": "2100"}, "open": {"day": 6, "time": "1000"}}]}, "place_id": "ChIJ4fd_MRpawokRHr3yLkECrOE", "formatted_phone_number": "(212) 284-9982", "formatted_address": "185 Greenwich St, New York, NY 10007, USA"}, {"rating": 4.2, "name": "Staten Island Mall", "geometry": {"location": {"lat": 40.5816575, "lng": -74.16608}, "viewport": {"northeast": {"lat": 40.5827226802915, "lng": -74.1644415697085}, "southwest": {"lat": 40.5800247197085, "lng": -74.16713953029151}}}, "opening_hours": {"weekday_text": ["Monday: 10:00 AM \u2013 9:00 PM", "Tuesday: 10:00 AM \u2013 9:00 PM", "Wednesday: 10:00 AM \u2013 9:00 PM", "Thursday: 10:00 AM \u2013 9:00 PM", "Friday: 10:00 AM \u2013 9:00 PM", "Saturday: 10:00 AM \u2013 9:00 PM", "Sunday: 11:00 AM \u2013 6:00 PM"], "open_now": false, "periods": [{"close": {"day": 0, "time": "1800"}, "open": {"day": 0, "time": "1100"}}, {"close": {"day": 1, "time": "2100"}, "open": {"day": 1, "time": "1000"}}, {"close": {"day": 2, "time": "2100"}, "open": {"day": 2, "time": "1000"}}, {"close": {"day": 3, "time": "2100"}, "open": {"day": 3, "time": "1000"}}, {"close": {"day": 4, "time": "2100"}, "open": {"day": 4, "time": "1000"}}, {"close": {"day": 5, "time": "2100"}, "open": {"day": 5, "time": "1000"}}, {"close": {"day": 6, "time": "2100"}, "open": {"day": 6, "time": "1000"}}]}, "place_id": "ChIJMQW5NIdLwokR8jmOUJsxtso", "formatted_phone_number": "(718) 761-6800", "formatted_address": "2655 Richmond Ave, Staten Island, NY 10314, USA"}, {"rating": 4.3, "name": "South Street Seaport", "geometry": {"location": {"lat": 40.7056185, "lng": -74.0027446}, "viewport": {"northeast": {"lat": 40.7072217802915, "lng": -74.0016794197085}, "southwest": {"lat": 40.70452381970851, "lng": -74.0043773802915}}}, "opening_hours": {"weekday_text": ["Monday: 11:00 AM \u2013 9:00 PM", "Tuesday: 11:00 AM \u2013 9:00 PM", "Wednesday: 11:00 AM \u2013 9:00 PM", "Thursday: 11:00 AM \u2013 9:00 PM", "Friday: 11:00 AM \u2013 9:00 PM", "Saturday: 11:00 AM \u2013 9:00 PM", "Sunday: 11:00 AM \u2013 9:00 PM"], "open_now": false, "periods": [{"close": {"day": 0, "time": "2100"}, "open": {"day": 0, "time": "1100"}}, {"close": {"day": 1, "time": "2100"}, "open": {"day": 1, "time": "1100"}}, {"close": {"day": 2, "time": "2100"}, "open": {"day": 2, "time": "1100"}}, {"close": {"day": 3, "time": "2100"}, "open": {"day": 3, "time": "1100"}}, {"close": {"day": 4, "time": "2100"}, "open": {"day": 4, "time": "1100"}}, {"close": {"day": 5, "time": "2100"}, "open": {"day": 5, "time": "1100"}}, {"close": {"day": 6, "time": "2100"}, "open": {"day": 6, "time": "1100"}}]}, "place_id": "ChIJ48y8-TxawokROJTPwB3cxz8", "formatted_phone_number": "(212) 732-8257", "formatted_address": "89 South St, New York, NY 10038, USA"}, {"rating": 4.4, "name": "Queens Center", "geometry": {"location": {"lat": 40.73468199999999, "lng": -73.8699788}, "viewport": {"northeast": {"lat": 40.7359409802915, "lng": -73.86832055000002}, "southwest": {"lat": 40.7332430197085, "lng": -73.87191514999999}}}, "opening_hours": {"weekday_text": ["Monday: 10:00 AM \u2013 9:30 PM", "Tuesday: 10:00 AM \u2013 9:30 PM", "Wednesday: 10:00 AM \u2013 9:30 PM", "Thursday: 10:00 AM \u2013 9:30 PM", "Friday: 10:00 AM \u2013 9:30 PM", "Saturday: 10:00 AM \u2013 9:30 PM", "Sunday: 11:00 AM \u2013 8:00 PM"], "open_now": false, "periods": [{"close": {"day": 0, "time": "2000"}, "open": {"day": 0, "time": "1100"}}, {"close": {"day": 1, "time": "2130"}, "open": {"day": 1, "time": "1000"}}, {"close": {"day": 2, "time": "2130"}, "open": {"day": 2, "time": "1000"}}, {"close": {"day": 3, "time": "2130"}, "open": {"day": 3, "time": "1000"}}, {"close": {"day": 4, "time": "2130"}, "open": {"day": 4, "time": "1000"}}, {"close": {"day": 5, "time": "2130"}, "open": {"day": 5, "time": "1000"}}, {"close": {"day": 6, "time": "2130"}, "open": {"day": 6, "time": "1000"}}]}, "place_id": "ChIJA7Ciw0tewokRWJrqRqhFJBs", "formatted_phone_number": "(718) 592-3900", "formatted_address": "90-15 Queens Blvd, Elmhurst, NY 11373, USA"}, {"rating": 4.4, "name": "The Mills at Jersey Gardens", "geometry": {"location": {"lat": 40.659951, "lng": -74.1710706}, "viewport": {"northeast": {"lat": 40.6617496302915, "lng": -74.16940406970849}, "southwest": {"lat": 40.6590516697085, "lng": -74.17210203029151}}}, "opening_hours": {"weekday_text": ["Monday: 10:00 AM \u2013 9:00 PM", "Tuesday: 10:00 AM \u2013 9:00 PM", "Wednesday: 10:00 AM \u2013 9:00 PM", "Thursday: 10:00 AM \u2013 9:00 PM", "Friday: 10:00 AM \u2013 9:00 PM", "Saturday: 10:00 AM \u2013 9:00 PM", "Sunday: 11:00 AM \u2013 7:00 PM"], "open_now": false, "periods": [{"close": {"day": 0, "time": "1900"}, "open": {"day": 0, "time": "1100"}}, {"close": {"day": 1, "time": "2100"}, "open": {"day": 1, "time": "1000"}}, {"close": {"day": 2, "time": "2100"}, "open": {"day": 2, "time": "1000"}}, {"close": {"day": 3, "time": "2100"}, "open": {"day": 3, "time": "1000"}}, {"close": {"day": 4, "time": "2100"}, "open": {"day": 4, "time": "1000"}}, {"close": {"day": 5, "time": "2100"}, "open": {"day": 5, "time": "1000"}}, {"close": {"day": 6, "time": "2100"}, "open": {"day": 6, "time": "1000"}}]}, "place_id": "ChIJixQeNIBNwokRItXUV8ujLjQ", "formatted_phone_number": "(908) 436-3005", "formatted_address": "651 Kapkowski Rd, Elizabeth, NJ 07201, USA"}, {"rating": 4.8, "name": "Michael's, The Consignment Shop for Women", "geometry": {"location": {"lat": 40.779633, "lng": -73.95926399999999}, "viewport": {"northeast": {"lat": 40.78105498029149, "lng": -73.9580931197085}, "southwest": {"lat": 40.77835701970849, "lng": -73.9607910802915}}}, "opening_hours": {"weekday_text": ["Monday: 10:00 AM \u2013 6:30 PM", "Tuesday: 10:00 AM \u2013 6:30 PM", "Wednesday: 10:00 AM \u2013 6:30 PM", "Thursday: 10:00 AM \u2013 8:00 PM", "Friday: 10:00 AM \u2013 6:30 PM", "Saturday: 10:00 AM \u2013 6:30 PM", "Sunday: 12:00 \u2013 6:00 PM"], "open_now": false, "periods": [{"close": {"day": 0, "time": "1800"}, "open": {"day": 0, "time": "1200"}}, {"close": {"day": 1, "time": "1830"}, "open": {"day": 1, "time": "1000"}}, {"close": {"day": 2, "time": "1830"}, "open": {"day": 2, "time": "1000"}}, {"close": {"day": 3, "time": "1830"}, "open": {"day": 3, "time": "1000"}}, {"close": {"day": 4, "time": "2000"}, "open": {"day": 4, "time": "1000"}}, {"close": {"day": 5, "time": "1830"}, "open": {"day": 5, "time": "1000"}}, {"close": {"day": 6, "time": "1830"}, "open": {"day": 6, "time": "1000"}}]}, "place_id": "ChIJCz0I15VYwokRWwJb-C1gnhA", "formatted_phone_number": "(212) 737-7273", "formatted_address": "1125 Madison Ave, New York, NY 10028, USA"}, {"rating": 4.2, "name": "Artists & Fleas SoHo", "geometry": {"location": {"lat": 40.724298, "lng": -73.997384}, "viewport": {"northeast": {"lat": 40.7257051802915, "lng": -73.99615421970849}, "southwest": {"lat": 40.7230072197085, "lng": -73.99885218029151}}}, "opening_hours": {"weekday_text": ["Monday: 11:00 AM \u2013 8:00 PM", "Tuesday: 11:00 AM \u2013 8:00 PM", "Wednesday: 11:00 AM \u2013 8:00 PM", "Thursday: 11:00 AM \u2013 8:00 PM", "Friday: 11:00 AM \u2013 8:00 PM", "Saturday: 11:00 AM \u2013 8:00 PM", "Sunday: 11:00 AM \u2013 8:00 PM"], "open_now": false, "periods": [{"close": {"day": 0, "time": "2000"}, "open": {"day": 0, "time": "1100"}}, {"close": {"day": 1, "time": "2000"}, "open": {"day": 1, "time": "1100"}}, {"close": {"day": 2, "time": "2000"}, "open": {"day": 2, "time": "1100"}}, {"close": {"day": 3, "time": "2000"}, "open": {"day": 3, "time": "1100"}}, {"close": {"day": 4, "time": "2000"}, "open": {"day": 4, "time": "1100"}}, {"close": {"day": 5, "time": "2000"}, "open": {"day": 5, "time": "1100"}}, {"close": {"day": 6, "time": "2000"}, "open": {"day": 6, "time": "1100"}}]}, "place_id": "ChIJh5ifHI9ZwokR_UFmNmGu77k", "formatted_phone_number": "(917) 767-6965", "formatted_address": "568 Broadway, New York, NY 10012, USA"}, {"rating": 3.5, "name": "Gabriella New York Bridal Salon", "geometry": {"location": {"lat": 40.7263585, "lng": -73.999425}, "viewport": {"northeast": {"lat": 40.7276836802915, "lng": -73.9980269697085}, "southwest": {"lat": 40.7249857197085, "lng": -74.00072493029151}}}, "opening_hours": {"weekday_text": ["Monday: 10:00 AM \u2013 6:00 PM", "Tuesday: 10:00 AM \u2013 6:00 PM", "Wednesday: 10:00 AM \u2013 6:00 PM", "Thursday: 10:00 AM \u2013 6:00 PM", "Friday: 10:00 AM \u2013 6:00 PM", "Saturday: 10:00 AM \u2013 6:00 PM", "Sunday: 10:00 AM \u2013 6:00 PM"], "open_now": false, "periods": [{"close": {"day": 0, "time": "1800"}, "open": {"day": 0, "time": "1000"}}, {"close": {"day": 1, "time": "1800"}, "open": {"day": 1, "time": "1000"}}, {"close": {"day": 2, "time": "1800"}, "open": {"day": 2, "time": "1000"}}, {"close": {"day": 3, "time": "1800"}, "open": {"day": 3, "time": "1000"}}, {"close": {"day": 4, "time": "1800"}, "open": {"day": 4, "time": "1000"}}, {"close": {"day": 5, "time": "1800"}, "open": {"day": 5, "time": "1000"}}, {"close": {"day": 6, "time": "1800"}, "open": {"day": 6, "time": "1000"}}]}, "place_id": "ChIJUa2ua45ZwokRuSqn852lHLw", "formatted_phone_number": "(212) 206-1915", "formatted_address": "155 Wooster St #3W, New York, NY 10012, USA"}, {"rating": 3.7, "name": "Creatures of Comfort", "geometry": {"location": {"lat": 40.721625, "lng": -73.99653099999999}, "viewport": {"northeast": {"lat": 40.7229607802915, "lng": -73.9951236197085}, "southwest": {"lat": 40.7202628197085, "lng": -73.9978215802915}}}, "opening_hours": {"weekday_text": ["Monday: 11:00 AM \u2013 7:00 PM", "Tuesday: 11:00 AM \u2013 7:00 PM", "Wednesday: 11:00 AM \u2013 7:00 PM", "Thursday: 11:00 AM \u2013 7:00 PM", "Friday: 11:00 AM \u2013 7:00 PM", "Saturday: 11:00 AM \u2013 7:00 PM", "Sunday: 12:00 \u2013 6:00 PM"], "open_now": false, "periods": [{"close": {"day": 0, "time": "1800"}, "open": {"day": 0, "time": "1200"}}, {"close": {"day": 1, "time": "1900"}, "open": {"day": 1, "time": "1100"}}, {"close": {"day": 2, "time": "1900"}, "open": {"day": 2, "time": "1100"}}, {"close": {"day": 3, "time": "1900"}, "open": {"day": 3, "time": "1100"}}, {"close": {"day": 4, "time": "1900"}, "open": {"day": 4, "time": "1100"}}, {"close": {"day": 5, "time": "1900"}, "open": {"day": 5, "time": "1100"}}, {"close": {"day": 6, "time": "1900"}, "open": {"day": 6, "time": "1100"}}]}, "place_id": "ChIJlysAx4hZwokRQ9n294wZZRw", "formatted_phone_number": "(212) 925-1005", "formatted_address": "205 Mulberry St, New York, NY 10012, USA"}, {"rating": 4.5, "name": "Diplomatic Duty Free Shops of New York", "geometry": {"location": {"lat": 40.752506, "lng": -73.969917}, "viewport": {"northeast": {"lat": 40.75390618029149, "lng": -73.9686896697085}, "southwest": {"lat": 40.7512082197085, "lng": -73.9713876302915}}}, "opening_hours": {"weekday_text": ["Monday: 9:30 AM \u2013 7:00 PM", "Tuesday: 9:30 AM \u2013 7:00 PM", "Wednesday: 9:30 AM \u2013 7:00 PM", "Thursday: 9:30 AM \u2013 7:00 PM", "Friday: 9:30 AM \u2013 7:00 PM", "Saturday: Closed", "Sunday: Closed"], "open_now": false, "periods": [{"close": {"day": 1, "time": "1900"}, "open": {"day": 1, "time": "0930"}}, {"close": {"day": 2, "time": "1900"}, "open": {"day": 2, "time": "0930"}}, {"close": {"day": 3, "time": "1900"}, "open": {"day": 3, "time": "0930"}}, {"close": {"day": 4, "time": "1900"}, "open": {"day": 4, "time": "0930"}}, {"close": {"day": 5, "time": "1900"}, "open": {"day": 5, "time": "0930"}}]}, "place_id": "ChIJIfKmQx1ZwokRAiuTngo5f_A", "formatted_phone_number": "(212) 838-9151", "formatted_address": "866 2nd Ave 2nd floor, New York, NY 10017, USA"}, {"rating": 4.7, "name": "Town Shop Lingerie- Bra Fittings", "geometry": {"location": {"lat": 40.785495, "lng": -73.97852}, "viewport": {"northeast": {"lat": 40.7868658302915, "lng": -73.97722276970849}, "southwest": {"lat": 40.7841678697085, "lng": -73.97992073029151}}}, "opening_hours": {"weekday_text": ["Monday: 10:00 AM \u2013 7:00 PM", "Tuesday: 10:00 AM \u2013 7:00 PM", "Wednesday: 10:00 AM \u2013 7:00 PM", "Thursday: 10:00 AM \u2013 7:00 PM", "Friday: 10:00 AM \u2013 7:00 PM", "Saturday: 9:30 AM \u2013 6:00 PM", "Sunday: 11:00 AM \u2013 6:00 PM"], "open_now": false, "periods": [{"close": {"day": 0, "time": "1800"}, "open": {"day": 0, "time": "1100"}}, {"close": {"day": 1, "time": "1900"}, "open": {"day": 1, "time": "1000"}}, {"close": {"day": 2, "time": "1900"}, "open": {"day": 2, "time": "1000"}}, {"close": {"day": 3, "time": "1900"}, "open": {"day": 3, "time": "1000"}}, {"close": {"day": 4, "time": "1900"}, "open": {"day": 4, "time": "1000"}}, {"close": {"day": 5, "time": "1900"}, "open": {"day": 5, "time": "1000"}}, {"close": {"day": 6, "time": "1800"}, "open": {"day": 6, "time": "0930"}}]}, "place_id": "ChIJ84o3QYZYwokRU4WDDB3U3xs", "formatted_phone_number": "(212) 595-6600", "formatted_address": "2270 Broadway, New York, NY 10024, USA"}, {"rating": 4.6, "name": "Jean Shop", "geometry": {"location": {"lat": 40.72094850000001, "lng": -73.9992418}, "viewport": {"northeast": {"lat": 40.7223299802915, "lng": -73.99796066970849}, "southwest": {"lat": 40.7196320197085, "lng": -74.0006586302915}}}, "opening_hours": {"weekday_text": ["Monday: 11:00 AM \u2013 7:00 PM", "Tuesday: 11:00 AM \u2013 7:00 PM", "Wednesday: 11:00 AM \u2013 7:00 PM", "Thursday: 11:00 AM \u2013 7:00 PM", "Friday: 11:00 AM \u2013 7:00 PM", "Saturday: 11:00 AM \u2013 7:00 PM", "Sunday: 12:00 \u2013 6:00 PM"], "open_now": false, "periods": [{"close": {"day": 0, "time": "1800"}, "open": {"day": 0, "time": "1200"}}, {"close": {"day": 1, "time": "1900"}, "open": {"day": 1, "time": "1100"}}, {"close": {"day": 2, "time": "1900"}, "open": {"day": 2, "time": "1100"}}, {"close": {"day": 3, "time": "1900"}, "open": {"day": 3, "time": "1100"}}, {"close": {"day": 4, "time": "1900"}, "open": {"day": 4, "time": "1100"}}, {"close": {"day": 5, "time": "1900"}, "open": {"day": 5, "time": "1100"}}, {"close": {"day": 6, "time": "1900"}, "open": {"day": 6, "time": "1100"}}]}, "place_id": "ChIJEceghMBZwokR-SL1kz_fs_c", "formatted_phone_number": "(212) 366-5326", "formatted_address": "37 Crosby St, New York, NY 10013, USA"}, {"rating": 4.3, "name": "Lovely Bride New York", "geometry": {"location": {"lat": 40.717149, "lng": -74.010093}, "viewport": {"northeast": {"lat": 40.7185751302915, "lng": -74.0086499697085}, "southwest": {"lat": 40.7158771697085, "lng": -74.0113479302915}}}, "opening_hours": {"weekday_text": ["Monday: Closed", "Tuesday: 9:30 AM \u2013 8:00 PM", "Wednesday: 9:30 AM \u2013 8:00 PM", "Thursday: 9:30 AM \u2013 8:00 PM", "Friday: 9:30 AM \u2013 8:00 PM", "Saturday: 9:00 AM \u2013 7:00 PM", "Sunday: 9:00 AM \u2013 7:00 PM"], "open_now": false, "periods": [{"close": {"day": 0, "time": "1900"}, "open": {"day": 0, "time": "0900"}}, {"close": {"day": 2, "time": "2000"}, "open": {"day": 2, "time": "0930"}}, {"close": {"day": 3, "time": "2000"}, "open": {"day": 3, "time": "0930"}}, {"close": {"day": 4, "time": "2000"}, "open": {"day": 4, "time": "0930"}}, {"close": {"day": 5, "time": "2000"}, "open": {"day": 5, "time": "0930"}}, {"close": {"day": 6, "time": "1900"}, "open": {"day": 6, "time": "0900"}}]}, "place_id": "ChIJ55edVx5awokRQSZUxYUFZd8", "formatted_phone_number": "(212) 924-2050", "formatted_address": "182 Duane St, New York, NY 10013, USA"}, {"rating": 3.3, "name": "Macy's eSpot Kiosk", "geometry": {"location": {"lat": 40.7597704, "lng": -73.82858759999999}, "viewport": {"northeast": {"lat": 40.7612017302915, "lng": -73.82727456970849}, "southwest": {"lat": 40.7585037697085, "lng": -73.82997253029151}}}, "opening_hours": {"weekday_text": ["Monday: 9:00 AM \u2013 9:00 PM", "Tuesday: 9:00 AM \u2013 9:00 PM", "Wednesday: 9:00 AM \u2013 9:00 PM", "Thursday: 9:00 AM \u2013 9:00 PM", "Friday: 9:00 AM \u2013 9:00 PM", "Saturday: 9:00 AM \u2013 9:00 PM", "Sunday: 9:00 AM \u2013 9:00 PM"], "open_now": false, "periods": [{"close": {"day": 0, "time": "2100"}, "open": {"day": 0, "time": "0900"}}, {"close": {"day": 1, "time": "2100"}, "open": {"day": 1, "time": "0900"}}, {"close": {"day": 2, "time": "2100"}, "open": {"day": 2, "time": "0900"}}, {"close": {"day": 3, "time": "2100"}, "open": {"day": 3, "time": "0900"}}, {"close": {"day": 4, "time": "2100"}, "open": {"day": 4, "time": "0900"}}, {"close": {"day": 5, "time": "2100"}, "open": {"day": 5, "time": "0900"}}, {"close": {"day": 6, "time": "2100"}, "open": {"day": 6, "time": "0900"}}]}, "place_id": "ChIJlQngsxFgwokR04_HhWdf0Hc", "formatted_phone_number": "(888) 314-4722", "formatted_address": "13650 Roosevelt Ave, Flushing, NY 11354, USA"}, {"rating": 4.4, "name": "New York Vintage Inc", "geometry": {"location": {"lat": 40.744631, "lng": -73.99261899999999}, "viewport": {"northeast": {"lat": 40.7459318302915, "lng": -73.99130556970849}, "southwest": {"lat": 40.7432338697085, "lng": -73.9940035302915}}}, "opening_hours": {"weekday_text": ["Monday: 11:00 AM \u2013 7:00 PM", "Tuesday: 11:00 AM \u2013 7:00 PM", "Wednesday: 11:00 AM \u2013 7:00 PM", "Thursday: 11:00 AM \u2013 7:00 PM", "Friday: 11:00 AM \u2013 7:00 PM", "Saturday: 10:00 AM \u2013 5:00 PM", "Sunday: Closed"], "open_now": false, "periods": [{"close": {"day": 1, "time": "1900"}, "open": {"day": 1, "time": "1100"}}, {"close": {"day": 2, "time": "1900"}, "open": {"day": 2, "time": "1100"}}, {"close": {"day": 3, "time": "1900"}, "open": {"day": 3, "time": "1100"}}, {"close": {"day": 4, "time": "1900"}, "open": {"day": 4, "time": "1100"}}, {"close": {"day": 5, "time": "1900"}, "open": {"day": 5, "time": "1100"}}, {"close": {"day": 6, "time": "1700"}, "open": {"day": 6, "time": "1000"}}]}, "place_id": "ChIJaQPEGqVZwokRIKb19abLH7A", "formatted_phone_number": "(212) 647-1107", "formatted_address": "117 W 25th St, New York, NY 10001, USA"}, {"rating": 4.2, "name": "The Shop at NBC Studios", "geometry": {"location": {"lat": 40.75932, "lng": -73.980058}, "viewport": {"northeast": {"lat": 40.76066898029151, "lng": -73.9787090197085}, "southwest": {"lat": 40.75797101970851, "lng": -73.98140698029151}}}, "opening_hours": {"weekday_text": ["Monday: 8:00 AM \u2013 9:00 PM", "Tuesday: 8:00 AM \u2013 9:00 PM", "Wednesday: 8:00 AM \u2013 9:00 PM", "Thursday: 8:00 AM \u2013 9:00 PM", "Friday: 8:00 AM \u2013 9:00 PM", "Saturday: 8:00 AM \u2013 9:00 PM", "Sunday: 8:00 AM \u2013 7:00 PM"], "open_now": false, "periods": [{"close": {"day": 0, "time": "1900"}, "open": {"day": 0, "time": "0800"}}, {"close": {"day": 1, "time": "2100"}, "open": {"day": 1, "time": "0800"}}, {"close": {"day": 2, "time": "2100"}, "open": {"day": 2, "time": "0800"}}, {"close": {"day": 3, "time": "2100"}, "open": {"day": 3, "time": "0800"}}, {"close": {"day": 4, "time": "2100"}, "open": {"day": 4, "time": "0800"}}, {"close": {"day": 5, "time": "2100"}, "open": {"day": 5, "time": "0800"}}, {"close": {"day": 6, "time": "2100"}, "open": {"day": 6, "time": "0800"}}]}, "place_id": "ChIJNZvR1v5YwokRadepdoJ17Vg", "formatted_phone_number": "(212) 664-2754", "formatted_address": "30 Rockefeller Plaza, New York, NY 10112, USA"}, {"rating": 3.8, "name": "Genes Caf\u00e9 Madison Avenue", "geometry": {"location": {"lat": 40.7646914, "lng": -73.9711429}, "viewport": {"northeast": {"lat": 40.7659530802915, "lng": -73.96959236970848}, "southwest": {"lat": 40.7632551197085, "lng": -73.9722903302915}}}, "opening_hours": {"weekday_text": ["Monday: 10:00 AM \u2013 8:00 PM", "Tuesday: 10:00 AM \u2013 8:00 PM", "Wednesday: 10:00 AM \u2013 8:00 PM", "Thursday: 10:00 AM \u2013 8:00 PM", "Friday: 10:00 AM \u2013 8:00 PM", "Saturday: 10:00 AM \u2013 7:00 PM", "Sunday: 11:00 AM \u2013 7:00 PM"], "open_now": false, "periods": [{"close": {"day": 0, "time": "1900"}, "open": {"day": 0, "time": "1100"}}, {"close": {"day": 1, "time": "2000"}, "open": {"day": 1, "time": "1000"}}, {"close": {"day": 2, "time": "2000"}, "open": {"day": 2, "time": "1000"}}, {"close": {"day": 3, "time": "2000"}, "open": {"day": 3, "time": "1000"}}, {"close": {"day": 4, "time": "2000"}, "open": {"day": 4, "time": "1000"}}, {"close": {"day": 5, "time": "2000"}, "open": {"day": 5, "time": "1000"}}, {"close": {"day": 6, "time": "1900"}, "open": {"day": 6, "time": "1000"}}]}, "place_id": "ChIJrekR3-9YwokRzwy1f2cu1So", "formatted_phone_number": "(212) 833-2022", "formatted_address": "660 Madison Ave Fl 8, New York, NY 10065, USA"}, {"rating": 4, "name": "Cobblestones", "geometry": {"location": {"lat": 40.72880159999999, "lng": -73.98654429999999}, "viewport": {"northeast": {"lat": 40.73018573029149, "lng": -73.98516891970849}, "southwest": {"lat": 40.72748776970849, "lng": -73.98786688029149}}}, "opening_hours": {"weekday_text": ["Monday: Closed", "Tuesday: 1:00 \u2013 7:00 PM", "Wednesday: 1:00 \u2013 7:00 PM", "Thursday: 1:00 \u2013 7:00 PM", "Friday: 1:00 \u2013 7:00 PM", "Saturday: 1:00 \u2013 7:00 PM", "Sunday: 1:00 \u2013 7:00 PM"], "open_now": false, "periods": [{"close": {"day": 0, "time": "1900"}, "open": {"day": 0, "time": "1300"}}, {"close": {"day": 2, "time": "1900"}, "open": {"day": 2, "time": "1300"}}, {"close": {"day": 3, "time": "1900"}, "open": {"day": 3, "time": "1300"}}, {"close": {"day": 4, "time": "1900"}, "open": {"day": 4, "time": "1300"}}, {"close": {"day": 5, "time": "1900"}, "open": {"day": 5, "time": "1300"}}, {"close": {"day": 6, "time": "1900"}, "open": {"day": 6, "time": "1300"}}]}, "place_id": "ChIJiynfUJxZwokRMxyZrmpvJ1I", "formatted_phone_number": "(212) 673-5372", "formatted_address": "314 E 9th St, New York, NY 10003, USA"}, {"rating": 4.1, "name": "Housing Works Thrift Shops", "geometry": {"location": {"lat": 40.7247093, "lng": -73.9963908}, "viewport": {"northeast": {"lat": 40.7260363802915, "lng": -73.99499721970848}, "southwest": {"lat": 40.7233384197085, "lng": -73.9976951802915}}}, "opening_hours": {"weekday_text": ["Monday: 11:00 AM \u2013 7:00 PM", "Tuesday: 11:00 AM \u2013 7:00 PM", "Wednesday: 11:00 AM \u2013 7:00 PM", "Thursday: 11:00 AM \u2013 7:00 PM", "Friday: 11:00 AM \u2013 7:00 PM", "Saturday: 11:00 AM \u2013 7:00 PM", "Sunday: 11:00 AM \u2013 5:00 PM"], "open_now": false, "periods": [{"close": {"day": 0, "time": "1700"}, "open": {"day": 0, "time": "1100"}}, {"close": {"day": 1, "time": "1900"}, "open": {"day": 1, "time": "1100"}}, {"close": {"day": 2, "time": "1900"}, "open": {"day": 2, "time": "1100"}}, {"close": {"day": 3, "time": "1900"}, "open": {"day": 3, "time": "1100"}}, {"close": {"day": 4, "time": "1900"}, "open": {"day": 4, "time": "1100"}}, {"close": {"day": 5, "time": "1900"}, "open": {"day": 5, "time": "1100"}}, {"close": {"day": 6, "time": "1900"}, "open": {"day": 6, "time": "1100"}}]}, "place_id": "ChIJ0WA5C49ZwokRlwCBkmzkUdo", "formatted_phone_number": "(646) 786-1200", "formatted_address": "130 Crosby St, New York, NY 10012, USA"}, {"rating": 4.8, "name": "SHOP UNTITLED", "geometry": {"location": {"lat": 40.7329667, "lng": -73.99776969999999}, "viewport": {"northeast": {"lat": 40.7342717302915, "lng": -73.9964541697085}, "southwest": {"lat": 40.7315737697085, "lng": -73.9991521302915}}}, "opening_hours": {"weekday_text": ["Monday: 11:30 AM \u2013 9:00 PM", "Tuesday: 11:30 AM \u2013 9:00 PM", "Wednesday: 11:30 AM \u2013 9:00 PM", "Thursday: 11:30 AM \u2013 9:00 PM", "Friday: 11:30 AM \u2013 9:00 PM", "Saturday: 11:30 AM \u2013 9:00 PM", "Sunday: 12:00 \u2013 9:00 PM"], "open_now": false, "periods": [{"close": {"day": 0, "time": "2100"}, "open": {"day": 0, "time": "1200"}}, {"close": {"day": 1, "time": "2100"}, "open": {"day": 1, "time": "1130"}}, {"close": {"day": 2, "time": "2100"}, "open": {"day": 2, "time": "1130"}}, {"close": {"day": 3, "time": "2100"}, "open": {"day": 3, "time": "1130"}}, {"close": {"day": 4, "time": "2100"}, "open": {"day": 4, "time": "1130"}}, {"close": {"day": 5, "time": "2100"}, "open": {"day": 5, "time": "1130"}}, {"close": {"day": 6, "time": "2100"}, "open": {"day": 6, "time": "1130"}}]}, "place_id": "ChIJc1jRK5dZwokRankYrf0jb88", "formatted_phone_number": "(212) 228-5166", "formatted_address": "27 W 8th St, New York, NY 10011, USA"}, {"rating": 5, "name": "Style Room NYC Shopping Tours", "geometry": {"location": {"lat": 40.7518134, "lng": -73.9916803}, "viewport": {"northeast": {"lat": 40.7530304302915, "lng": -73.9904307697085}, "southwest": {"lat": 40.7503324697085, "lng": -73.9931287302915}}}, "place_id": "ChIJSfvCLKxZwokRJMq5NzUVYoc", "formatted_phone_number": "(646) 245-5316", "formatted_address": "225 W 34th St, New York, NY 10122, USA"}, {"rating": 4.6, "name": "Housing Works Thrift Shops", "geometry": {"location": {"lat": 40.7339353, "lng": -74.0058945}, "viewport": {"northeast": {"lat": 40.7352231302915, "lng": -74.00452951970848}, "southwest": {"lat": 40.7325251697085, "lng": -74.00722748029149}}}, "opening_hours": {"weekday_text": ["Monday: 11:00 AM \u2013 7:00 PM", "Tuesday: 11:00 AM \u2013 7:00 PM", "Wednesday: 11:00 AM \u2013 7:00 PM", "Thursday: 11:00 AM \u2013 7:00 PM", "Friday: 11:00 AM \u2013 7:00 PM", "Saturday: 11:00 AM \u2013 7:00 PM", "Sunday: 11:00 AM \u2013 5:00 PM"], "open_now": false, "periods": [{"close": {"day": 0, "time": "1700"}, "open": {"day": 0, "time": "1100"}}, {"close": {"day": 1, "time": "1900"}, "open": {"day": 1, "time": "1100"}}, {"close": {"day": 2, "time": "1900"}, "open": {"day": 2, "time": "1100"}}, {"close": {"day": 3, "time": "1900"}, "open": {"day": 3, "time": "1100"}}, {"close": {"day": 4, "time": "1900"}, "open": {"day": 4, "time": "1100"}}, {"close": {"day": 5, "time": "1900"}, "open": {"day": 5, "time": "1100"}}, {"close": {"day": 6, "time": "1900"}, "open": {"day": 6, "time": "1100"}}]}, "place_id": "ChIJo_reqJRZwokRAHCtJNsmaXM", "formatted_phone_number": "(212) 352-1618", "formatted_address": "245 W 10th St, New York, NY 10014, USA"}, {"rating": 4.7, "name": "The Hat Shop", "geometry": {"location": {"lat": 40.7259702, "lng": -74.00157639999999}, "viewport": {"northeast": {"lat": 40.7273463302915, "lng": -74.00028466970849}, "southwest": {"lat": 40.7246483697085, "lng": -74.0029826302915}}}, "opening_hours": {"weekday_text": ["Monday: 12:00 \u2013 7:00 PM", "Tuesday: 12:00 \u2013 7:00 PM", "Wednesday: 12:00 \u2013 7:00 PM", "Thursday: 12:00 \u2013 7:00 PM", "Friday: 12:00 \u2013 7:00 PM", "Saturday: 12:00 \u2013 7:00 PM", "Sunday: 1:00 \u2013 6:00 PM"], "open_now": false, "periods": [{"close": {"day": 0, "time": "1800"}, "open": {"day": 0, "time": "1300"}}, {"close": {"day": 1, "time": "1900"}, "open": {"day": 1, "time": "1200"}}, {"close": {"day": 2, "time": "1900"}, "open": {"day": 2, "time": "1200"}}, {"close": {"day": 3, "time": "1900"}, "open": {"day": 3, "time": "1200"}}, {"close": {"day": 4, "time": "1900"}, "open": {"day": 4, "time": "1200"}}, {"close": {"day": 5, "time": "1900"}, "open": {"day": 5, "time": "1200"}}, {"close": {"day": 6, "time": "1900"}, "open": {"day": 6, "time": "1200"}}]}, "place_id": "ChIJGfIczI1ZwokRTQYwO6wDF04", "formatted_phone_number": "(212) 219-1445", "formatted_address": "120 Thompson St, New York, NY 10012, USA"}, {"rating": 4.2, "name": "Housing Works Thrift Shops", "geometry": {"location": {"lat": 40.7951431, "lng": -73.97176879999999}, "viewport": {"northeast": {"lat": 40.7964628302915, "lng": -73.9703532697085}, "southwest": {"lat": 40.7937648697085, "lng": -73.9730512302915}}}, "opening_hours": {"weekday_text": ["Monday: 11:00 AM \u2013 7:00 PM", "Tuesday: 11:00 AM \u2013 7:00 PM", "Wednesday: 11:00 AM \u2013 7:00 PM", "Thursday: 11:00 AM \u2013 7:00 PM", "Friday: 11:00 AM \u2013 7:00 PM", "Saturday: 11:00 AM \u2013 7:00 PM", "Sunday: 12:00 \u2013 6:00 PM"], "open_now": false, "periods": [{"close": {"day": 0, "time": "1800"}, "open": {"day": 0, "time": "1200"}}, {"close": {"day": 1, "time": "1900"}, "open": {"day": 1, "time": "1100"}}, {"close": {"day": 2, "time": "1900"}, "open": {"day": 2, "time": "1100"}}, {"close": {"day": 3, "time": "1900"}, "open": {"day": 3, "time": "1100"}}, {"close": {"day": 4, "time": "1900"}, "open": {"day": 4, "time": "1100"}}, {"close": {"day": 5, "time": "1900"}, "open": {"day": 5, "time": "1100"}}, {"close": {"day": 6, "time": "1900"}, "open": {"day": 6, "time": "1100"}}]}, "place_id": "ChIJEbZQeSj2wokR2SRfjJHS408", "formatted_phone_number": "(212) 222-3550", "formatted_address": "2569 Broadway, New York, NY 10025, USA"}, {"rating": 5, "name": "ZTrend New York Shopping Tours", "geometry": {"location": {"lat": 40.74565390000001, "lng": -73.9884615}, "viewport": {"northeast": {"lat": 40.7470145302915, "lng": -73.98721156970849}, "southwest": {"lat": 40.7443165697085, "lng": -73.9899095302915}}}, "opening_hours": {"weekday_text": ["Monday: 9:00 AM \u2013 5:00 PM", "Tuesday: 9:00 AM \u2013 7:00 PM", "Wednesday: 9:00 AM \u2013 7:00 AM", "Thursday: 9:00 AM \u2013 7:00 PM", "Friday: 9:00 AM \u2013 7:00 PM", "Saturday: 9:00 AM \u2013 7:00 PM", "Sunday: 9:00 AM \u2013 7:00 AM"], "open_now": false, "periods": [{"close": {"day": 1, "time": "0700"}, "open": {"day": 0, "time": "0900"}}, {"close": {"day": 1, "time": "1700"}, "open": {"day": 1, "time": "0900"}}, {"close": {"day": 2, "time": "1900"}, "open": {"day": 2, "time": "0900"}}, {"close": {"day": 4, "time": "0700"}, "open": {"day": 3, "time": "0900"}}, {"close": {"day": 4, "time": "1900"}, "open": {"day": 4, "time": "0900"}}, {"close": {"day": 5, "time": "1900"}, "open": {"day": 5, "time": "0900"}}, {"close": {"day": 6, "time": "1900"}, "open": {"day": 6, "time": "0900"}}]}, "place_id": "ChIJsWyiBKZZwokRk2cvdrMELXY", "formatted_phone_number": "(424) 666-8849", "formatted_address": "1186 Broadway, New York, NY 10001, USA"}, {"rating": 4.6, "name": "The New York Public Library Shop", "geometry": {"location": {"lat": 40.75246000000001, "lng": -73.9811434}, "viewport": {"northeast": {"lat": 40.75388803029151, "lng": -73.97998576970849}, "southwest": {"lat": 40.75119006970851, "lng": -73.9826837302915}}}, "opening_hours": {"weekday_text": ["Monday: 10:00 AM \u2013 6:00 PM", "Tuesday: 10:00 AM \u2013 6:00 PM", "Wednesday: 10:00 AM \u2013 6:00 PM", "Thursday: 10:00 AM \u2013 6:00 PM", "Friday: 10:00 AM \u2013 6:00 PM", "Saturday: 10:00 AM \u2013 6:00 PM", "Sunday: Closed"], "open_now": false, "periods": [{"close": {"day": 1, "time": "1800"}, "open": {"day": 1, "time": "1000"}}, {"close": {"day": 2, "time": "1800"}, "open": {"day": 2, "time": "1000"}}, {"close": {"day": 3, "time": "1800"}, "open": {"day": 3, "time": "1000"}}, {"close": {"day": 4, "time": "1800"}, "open": {"day": 4, "time": "1000"}}, {"close": {"day": 5, "time": "1800"}, "open": {"day": 5, "time": "1000"}}, {"close": {"day": 6, "time": "1800"}, "open": {"day": 6, "time": "1000"}}]}, "place_id": "ChIJJcFX6alZwokRPElLWaXkTeA", "formatted_phone_number": "(212) 930-0869", "formatted_address": "475 5th Ave, New York, NY 10018, USA"}, {"rating": 3.8, "name": "Limelight Shops", "geometry": {"location": {"lat": 40.7410753, "lng": -73.9937405}, "viewport": {"northeast": {"lat": 40.74233908029149, "lng": -73.99245396970849}, "southwest": {"lat": 40.7396411197085, "lng": -73.9951519302915}}}, "opening_hours": {"weekday_text": ["Monday: 10:00 AM \u2013 9:00 PM", "Tuesday: 10:00 AM \u2013 9:00 PM", "Wednesday: 10:00 AM \u2013 9:00 PM", "Thursday: 10:00 AM \u2013 9:00 PM", "Friday: 10:00 AM \u2013 9:00 PM", "Saturday: 10:00 AM \u2013 9:00 PM", "Sunday: 11:00 AM \u2013 8:00 PM"], "open_now": false, "periods": [{"close": {"day": 0, "time": "2000"}, "open": {"day": 0, "time": "1100"}}, {"close": {"day": 1, "time": "2100"}, "open": {"day": 1, "time": "1000"}}, {"close": {"day": 2, "time": "2100"}, "open": {"day": 2, "time": "1000"}}, {"close": {"day": 3, "time": "2100"}, "open": {"day": 3, "time": "1000"}}, {"close": {"day": 4, "time": "2100"}, "open": {"day": 4, "time": "1000"}}, {"close": {"day": 5, "time": "2100"}, "open": {"day": 5, "time": "1000"}}, {"close": {"day": 6, "time": "2100"}, "open": {"day": 6, "time": "1000"}}]}, "place_id": "ChIJhbETRaNZwokRYxrLpnVTijg", "formatted_phone_number": "(212) 255-2144", "formatted_address": "47 W 20th St, New York, NY 10011, USA"}, {"rating": 4.8, "name": "Raaka Chocolate", "geometry": {"location": {"lat": 40.68143670000001, "lng": -74.0071505}, "viewport": {"northeast": {"lat": 40.6826839302915, "lng": -74.0059233697085}, "southwest": {"lat": 40.6799859697085, "lng": -74.0086213302915}}}, "opening_hours": {"weekday_text": ["Monday: 10:00 AM \u2013 5:00 PM", "Tuesday: 10:00 AM \u2013 5:00 PM", "Wednesday: 10:00 AM \u2013 5:00 PM", "Thursday: 10:00 AM \u2013 5:00 PM", "Friday: 10:00 AM \u2013 5:00 PM", "Saturday: 12:00 \u2013 6:00 PM", "Sunday: 12:00 \u2013 6:00 PM"], "open_now": false, "periods": [{"close": {"day": 0, "time": "1800"}, "open": {"day": 0, "time": "1200"}}, {"close": {"day": 1, "time": "1700"}, "open": {"day": 1, "time": "1000"}}, {"close": {"day": 2, "time": "1700"}, "open": {"day": 2, "time": "1000"}}, {"close": {"day": 3, "time": "1700"}, "open": {"day": 3, "time": "1000"}}, {"close": {"day": 4, "time": "1700"}, "open": {"day": 4, "time": "1000"}}, {"close": {"day": 5, "time": "1700"}, "open": {"day": 5, "time": "1000"}}, {"close": {"day": 6, "time": "1800"}, "open": {"day": 6, "time": "1200"}}]}, "place_id": "ChIJFyq4ScFbwokRwMJWGE6ad1o", "formatted_phone_number": "(855) 255-3354", "formatted_address": "64 Seabring St, Brooklyn, NY 11231, USA"}, {"rating": 4.7, "name": "The Plaza Boutique", "geometry": {"location": {"lat": 40.7641638, "lng": -73.97445689999999}, "viewport": {"northeast": {"lat": 40.76547568029149, "lng": -73.97313481970849}, "southwest": {"lat": 40.7627777197085, "lng": -73.9758327802915}}}, "opening_hours": {"open_now": false}, "place_id": "ChIJXeTBhfBYwokRz6A4gM1j3_k", "formatted_phone_number": "(212) 546-5454", "formatted_address": "The Plaza Hotel, 1 W 58th St, New York, NY 10019, USA"}, {"rating": 4.1, "name": "Designer Loft", "geometry": {"location": {"lat": 40.75330999999999, "lng": -73.99059199999999}, "viewport": {"northeast": {"lat": 40.7546589802915, "lng": -73.98924301970848}, "southwest": {"lat": 40.7519610197085, "lng": -73.9919409802915}}}, "opening_hours": {"weekday_text": ["Monday: 11:00 AM \u2013 6:00 PM", "Tuesday: 11:00 AM \u2013 6:00 PM", "Wednesday: 11:00 AM \u2013 6:00 PM", "Thursday: 11:00 AM \u2013 6:00 PM", "Friday: 11:00 AM \u2013 6:00 PM", "Saturday: 10:00 AM \u2013 5:00 PM", "Sunday: 11:00 AM \u2013 5:00 PM"], "open_now": false, "periods": [{"close": {"day": 0, "time": "1700"}, "open": {"day": 0, "time": "1100"}}, {"close": {"day": 1, "time": "1800"}, "open": {"day": 1, "time": "1100"}}, {"close": {"day": 2, "time": "1800"}, "open": {"day": 2, "time": "1100"}}, {"close": {"day": 3, "time": "1800"}, "open": {"day": 3, "time": "1100"}}, {"close": {"day": 4, "time": "1800"}, "open": {"day": 4, "time": "1100"}}, {"close": {"day": 5, "time": "1800"}, "open": {"day": 5, "time": "1100"}}, {"close": {"day": 6, "time": "1700"}, "open": {"day": 6, "time": "1000"}}]}, "place_id": "ChIJr_LzXKxZwokRp5lz8T6it58", "formatted_phone_number": "(212) 944-9013", "formatted_address": "226 W 37th St, Second Floor, New York, NY 10018, USA"}, {"rating": 4.6, "name": "Fragrance Shop New York", "geometry": {"location": {"lat": 40.726808, "lng": -73.99067289999999}, "viewport": {"northeast": {"lat": 40.7281247302915, "lng": -73.9893478697085}, "southwest": {"lat": 40.7254267697085, "lng": -73.9920458302915}}}, "opening_hours": {"weekday_text": ["Monday: 11:00 AM \u2013 7:00 PM", "Tuesday: 11:00 AM \u2013 7:00 PM", "Wednesday: 11:00 AM \u2013 7:00 PM", "Thursday: 11:00 AM \u2013 7:00 PM", "Friday: 11:00 AM \u2013 7:00 PM", "Saturday: 12:00 \u2013 7:00 PM", "Sunday: Closed"], "open_now": false, "periods": [{"close": {"day": 1, "time": "1900"}, "open": {"day": 1, "time": "1100"}}, {"close": {"day": 2, "time": "1900"}, "open": {"day": 2, "time": "1100"}}, {"close": {"day": 3, "time": "1900"}, "open": {"day": 3, "time": "1100"}}, {"close": {"day": 4, "time": "1900"}, "open": {"day": 4, "time": "1100"}}, {"close": {"day": 5, "time": "1900"}, "open": {"day": 5, "time": "1100"}}, {"close": {"day": 6, "time": "1900"}, "open": {"day": 6, "time": "1200"}}]}, "place_id": "ChIJC-foeZtZwokRQrBWLT3le88", "formatted_phone_number": "(212) 254-8950", "formatted_address": "65 E 4th St, New York, NY 10003, USA"}, {"rating": 3.8, "name": "Housing Works Thrift Shops", "geometry": {"location": {"lat": 40.7154113, "lng": -74.00842899999999}, "viewport": {"northeast": {"lat": 40.7166645302915, "lng": -74.0071555697085}, "southwest": {"lat": 40.7139665697085, "lng": -74.00985353029151}}}, "opening_hours": {"weekday_text": ["Monday: 12:00 \u2013 7:00 PM", "Tuesday: 12:00 \u2013 7:00 PM", "Wednesday: 12:00 \u2013 7:00 PM", "Thursday: 12:00 \u2013 7:00 PM", "Friday: 12:00 \u2013 7:00 PM", "Saturday: 12:00 \u2013 5:00 PM", "Sunday: 12:00 \u2013 5:00 PM"], "open_now": false, "periods": [{"close": {"day": 0, "time": "1700"}, "open": {"day": 0, "time": "1200"}}, {"close": {"day": 1, "time": "1900"}, "open": {"day": 1, "time": "1200"}}, {"close": {"day": 2, "time": "1900"}, "open": {"day": 2, "time": "1200"}}, {"close": {"day": 3, "time": "1900"}, "open": {"day": 3, "time": "1200"}}, {"close": {"day": 4, "time": "1900"}, "open": {"day": 4, "time": "1200"}}, {"close": {"day": 5, "time": "1900"}, "open": {"day": 5, "time": "1200"}}, {"close": {"day": 6, "time": "1700"}, "open": {"day": 6, "time": "1200"}}]}, "place_id": "ChIJG2DVFx9awokRaIrPM2exvaU", "formatted_phone_number": "(212) 732-0584", "formatted_address": "119 Chambers St, New York, NY 10007, USA"}, {"name": "T-Pop Shop NYC", "geometry": {"location": {"lat": 40.717346, "lng": -74.003337}, "viewport": {"northeast": {"lat": 40.71867718029149, "lng": -74.0020034697085}, "southwest": {"lat": 40.71597921970849, "lng": -74.0047014302915}}}, "opening_hours": {"weekday_text": ["Monday: Open 24 hours", "Tuesday: Open 24 hours", "Wednesday: Open 24 hours", "Thursday: Open 24 hours", "Friday: Open 24 hours", "Saturday: Open 24 hours", "Sunday: Open 24 hours"], "open_now": true, "periods": [{"open": {"day": 0, "time": "0000"}}]}, "place_id": "ChIJ1UgPiyBawokRFG48GADz120", "formatted_phone_number": "(917) 582-0701", "formatted_address": "59 Franklin St, New York, NY 10013, USA"}, {"rating": 4.6, "name": "NYC Velo", "geometry": {"location": {"lat": 40.7258825, "lng": -73.9893093}, "viewport": {"northeast": {"lat": 40.7272906302915, "lng": -73.98810036970849}, "southwest": {"lat": 40.7245926697085, "lng": -73.9907983302915}}}, "opening_hours": {"weekday_text": ["Monday: 11:00 AM \u2013 8:00 PM", "Tuesday: 11:00 AM \u2013 8:00 PM", "Wednesday: 11:00 AM \u2013 8:00 PM", "Thursday: 11:00 AM \u2013 8:00 PM", "Friday: 11:00 AM \u2013 8:00 PM", "Saturday: 11:00 AM \u2013 6:00 PM", "Sunday: 11:00 AM \u2013 6:00 PM"], "open_now": false, "periods": [{"close": {"day": 0, "time": "1800"}, "open": {"day": 0, "time": "1100"}}, {"close": {"day": 1, "time": "2000"}, "open": {"day": 1, "time": "1100"}}, {"close": {"day": 2, "time": "2000"}, "open": {"day": 2, "time": "1100"}}, {"close": {"day": 3, "time": "2000"}, "open": {"day": 3, "time": "1100"}}, {"close": {"day": 4, "time": "2000"}, "open": {"day": 4, "time": "1100"}}, {"close": {"day": 5, "time": "2000"}, "open": {"day": 5, "time": "1100"}}, {"close": {"day": 6, "time": "1800"}, "open": {"day": 6, "time": "1100"}}]}, "place_id": "ChIJ0Tw5r4RZwokRiO2CpQQA1m0", "formatted_phone_number": "(212) 253-7771", "formatted_address": "66 2nd Ave, New York, NY 10003, USA"}, {"rating": 4.5, "name": "NYC Velo Hell's Kitchen", "geometry": {"location": {"lat": 40.7625199, "lng": -73.9966348}, "viewport": {"northeast": {"lat": 40.7639116302915, "lng": -73.99525456970851}, "southwest": {"lat": 40.7612136697085, "lng": -73.99795253029151}}}, "opening_hours": {"weekday_text": ["Monday: 9:00 AM \u2013 8:00 PM", "Tuesday: 9:00 AM \u2013 8:00 PM", "Wednesday: 9:00 AM \u2013 8:00 PM", "Thursday: 9:00 AM \u2013 8:00 PM", "Friday: 9:00 AM \u2013 8:00 PM", "Saturday: 9:00 AM \u2013 8:00 PM", "Sunday: 10:00 AM \u2013 8:00 PM"], "open_now": false, "periods": [{"close": {"day": 0, "time": "2000"}, "open": {"day": 0, "time": "1000"}}, {"close": {"day": 1, "time": "2000"}, "open": {"day": 1, "time": "0900"}}, {"close": {"day": 2, "time": "2000"}, "open": {"day": 2, "time": "0900"}}, {"close": {"day": 3, "time": "2000"}, "open": {"day": 3, "time": "0900"}}, {"close": {"day": 4, "time": "2000"}, "open": {"day": 4, "time": "0900"}}, {"close": {"day": 5, "time": "2000"}, "open": {"day": 5, "time": "0900"}}, {"close": {"day": 6, "time": "2000"}, "open": {"day": 6, "time": "0900"}}]}, "place_id": "ChIJHaHScU5YwokRLT4Io-to9Pc", "formatted_phone_number": "(212) 582-7949", "formatted_address": "590 W 45th St, New York, NY 10036, USA"}, {"rating": 4.7, "name": "Time Square", "geometry": {"location": {"lat": 40.7536704, "lng": -73.9946686}, "viewport": {"northeast": {"lat": 40.7549803802915, "lng": -73.99334821970851}, "southwest": {"lat": 40.7522824197085, "lng": -73.99604618029151}}}, "opening_hours": {"open_now": false}, "place_id": "ChIJu2zgh61ZwokRu-BPG0fOCh8", "formatted_address": "345 W 35th St, New York, NY 10001, USA"}, {"rating": 4.4, "name": "Dover Street Market New York", "geometry": {"location": {"lat": 40.7440962, "lng": -73.9817188}, "viewport": {"northeast": {"lat": 40.7453946802915, "lng": -73.9802452697085}, "southwest": {"lat": 40.7426967197085, "lng": -73.98294323029151}}}, "opening_hours": {"weekday_text": ["Monday: 11:00 AM \u2013 7:00 PM", "Tuesday: 11:00 AM \u2013 7:00 PM", "Wednesday: 11:00 AM \u2013 7:00 PM", "Thursday: 11:00 AM \u2013 7:00 PM", "Friday: 11:00 AM \u2013 7:00 PM", "Saturday: 11:00 AM \u2013 7:00 PM", "Sunday: 12:00 \u2013 6:00 PM"], "open_now": false, "periods": [{"close": {"day": 0, "time": "1800"}, "open": {"day": 0, "time": "1200"}}, {"close": {"day": 1, "time": "1900"}, "open": {"day": 1, "time": "1100"}}, {"close": {"day": 2, "time": "1900"}, "open": {"day": 2, "time": "1100"}}, {"close": {"day": 3, "time": "1900"}, "open": {"day": 3, "time": "1100"}}, {"close": {"day": 4, "time": "1900"}, "open": {"day": 4, "time": "1100"}}, {"close": {"day": 5, "time": "1900"}, "open": {"day": 5, "time": "1100"}}, {"close": {"day": 6, "time": "1900"}, "open": {"day": 6, "time": "1100"}}]}, "place_id": "ChIJTS9-FAhZwokRcbse7lr_jHA", "formatted_phone_number": "(646) 837-7750", "formatted_address": "160 Lexington Ave, New York, NY 10016, USA"}, {"rating": 4.5, "name": "Brookfield Place", "geometry": {"location": {"lat": 40.7127168, "lng": -74.01528239999999}, "viewport": {"northeast": {"lat": 40.7159453, "lng": -74.0106163}, "southwest": {"lat": 40.7092894, "lng": -74.0202497}}}, "opening_hours": {"weekday_text": ["Monday: 10:00 AM \u2013 8:00 PM", "Tuesday: 10:00 AM \u2013 8:00 PM", "Wednesday: 10:00 AM \u2013 8:00 PM", "Thursday: 10:00 AM \u2013 8:00 PM", "Friday: 10:00 AM \u2013 8:00 PM", "Saturday: 10:00 AM \u2013 8:00 PM", "Sunday: 12:00 \u2013 6:00 PM"], "open_now": false, "periods": [{"close": {"day": 0, "time": "1800"}, "open": {"day": 0, "time": "1200"}}, {"close": {"day": 1, "time": "2000"}, "open": {"day": 1, "time": "1000"}}, {"close": {"day": 2, "time": "2000"}, "open": {"day": 2, "time": "1000"}}, {"close": {"day": 3, "time": "2000"}, "open": {"day": 3, "time": "1000"}}, {"close": {"day": 4, "time": "2000"}, "open": {"day": 4, "time": "1000"}}, {"close": {"day": 5, "time": "2000"}, "open": {"day": 5, "time": "1000"}}, {"close": {"day": 6, "time": "2000"}, "open": {"day": 6, "time": "1000"}}]}, "place_id": "ChIJy8jTDBtawokRB9wNyxemSw8", "formatted_phone_number": "(212) 978-1673", "formatted_address": "230 Vesey St, New York, NY 10281, USA"}, {"rating": 2.3, "name": "Necessary Clothing", "geometry": {"location": {"lat": 40.720157, "lng": -74.0010544}, "viewport": {"northeast": {"lat": 40.7215379802915, "lng": -73.9997716197085}, "southwest": {"lat": 40.7188400197085, "lng": -74.0024695802915}}}, "opening_hours": {"weekday_text": ["Monday: 10:00 AM \u2013 9:00 PM", "Tuesday: 10:00 AM \u2013 9:00 PM", "Wednesday: 10:00 AM \u2013 9:00 PM", "Thursday: 10:00 AM \u2013 9:00 PM", "Friday: 10:00 AM \u2013 9:00 PM", "Saturday: 10:00 AM \u2013 9:00 PM", "Sunday: 10:00 AM \u2013 8:00 PM"], "open_now": false, "periods": [{"close": {"day": 0, "time": "2000"}, "open": {"day": 0, "time": "1000"}}, {"close": {"day": 1, "time": "2100"}, "open": {"day": 1, "time": "1000"}}, {"close": {"day": 2, "time": "2100"}, "open": {"day": 2, "time": "1000"}}, {"close": {"day": 3, "time": "2100"}, "open": {"day": 3, "time": "1000"}}, {"close": {"day": 4, "time": "2100"}, "open": {"day": 4, "time": "1000"}}, {"close": {"day": 5, "time": "2100"}, "open": {"day": 5, "time": "1000"}}, {"close": {"day": 6, "time": "2100"}, "open": {"day": 6, "time": "1000"}}]}, "place_id": "ChIJt41PJopZwokRacUl10saeGA", "formatted_address": "443 Broadway, New York, NY 10013, USA"}, {"rating": 4.2, "name": "NYC Smoke Shop & Vape Shop", "geometry": {"location": {"lat": 40.7098644, "lng": -74.0090517}, "viewport": {"northeast": {"lat": 40.7112461302915, "lng": -74.00766131970849}, "southwest": {"lat": 40.7085481697085, "lng": -74.01035928029151}}}, "opening_hours": {"weekday_text": ["Monday: 7:00 AM \u2013 11:00 PM", "Tuesday: 7:00 AM \u2013 11:00 PM", "Wednesday: 7:00 AM \u2013 11:00 PM", "Thursday: 7:00 AM \u2013 12:00 AM", "Friday: 7:00 AM \u2013 12:00 AM", "Saturday: 7:00 AM \u2013 12:00 AM", "Sunday: 7:00 AM \u2013 11:00 PM"], "open_now": false, "periods": [{"close": {"day": 0, "time": "2300"}, "open": {"day": 0, "time": "0700"}}, {"close": {"day": 1, "time": "2300"}, "open": {"day": 1, "time": "0700"}}, {"close": {"day": 2, "time": "2300"}, "open": {"day": 2, "time": "0700"}}, {"close": {"day": 3, "time": "2300"}, "open": {"day": 3, "time": "0700"}}, {"close": {"day": 5, "time": "0000"}, "open": {"day": 4, "time": "0700"}}, {"close": {"day": 6, "time": "0000"}, "open": {"day": 5, "time": "0700"}}, {"close": {"day": 0, "time": "0000"}, "open": {"day": 6, "time": "0700"}}]}, "place_id": "ChIJ5f4tLBhawokRut96Q4N690k", "formatted_phone_number": "(646) 964-5469", "formatted_address": "12 John St, New York, NY 10038, USA"}, {"geometry": {"location": {"lat": 40.7184706, "lng": -73.9948124}, "viewport": {"northeast": {"lat": 40.71981958029151, "lng": -73.99346341970849}, "southwest": {"lat": 40.71712161970851, "lng": -73.99616138029151}}}, "opening_hours": {"open_now": false}, "place_id": "ChIJt-CyCohZwokRARlkL446WW0", "formatted_address": "Bowery & Grand St, New York, NY 10013, USA", "name": "Grand St & Bowery, Manhattan, NY"}, {"rating": 4.6, "name": "The Seaport District", "geometry": {"location": {"lat": 40.7070877, "lng": -74.003546}, "viewport": {"northeast": {"lat": 40.7083921802915, "lng": -74.00230816970848}, "southwest": {"lat": 40.7056942197085, "lng": -74.0050061302915}}}, "opening_hours": {"weekday_text": ["Monday: 11:00 AM \u2013 9:00 PM", "Tuesday: 11:00 AM \u2013 9:00 PM", "Wednesday: 11:00 AM \u2013 9:00 PM", "Thursday: 11:00 AM \u2013 9:00 PM", "Friday: 11:00 AM \u2013 9:00 PM", "Saturday: 11:00 AM \u2013 9:00 PM", "Sunday: 11:00 AM \u2013 9:00 PM"], "open_now": false, "periods": [{"close": {"day": 0, "time": "2100"}, "open": {"day": 0, "time": "1100"}}, {"close": {"day": 1, "time": "2100"}, "open": {"day": 1, "time": "1100"}}, {"close": {"day": 2, "time": "2100"}, "open": {"day": 2, "time": "1100"}}, {"close": {"day": 3, "time": "2100"}, "open": {"day": 3, "time": "1100"}}, {"close": {"day": 4, "time": "2100"}, "open": {"day": 4, "time": "1100"}}, {"close": {"day": 5, "time": "2100"}, "open": {"day": 5, "time": "1100"}}, {"close": {"day": 6, "time": "2100"}, "open": {"day": 6, "time": "1100"}}]}, "place_id": "ChIJh6Pk4TxawokRQn2vBz09L-M", "formatted_phone_number": "(646) 822-6972", "formatted_address": "19 Fulton St, New York, NY 10038, USA"}, {"rating": 4.3, "name": "Artists & Fleas", "geometry": {"location": {"lat": 40.7428772, "lng": -74.00737409999999}, "viewport": {"northeast": {"lat": 40.7442261802915, "lng": -74.0060251197085}, "southwest": {"lat": 40.7415282197085, "lng": -74.0087230802915}}}, "opening_hours": {"weekday_text": ["Monday: 10:00 AM \u2013 9:00 PM", "Tuesday: 10:00 AM \u2013 9:00 PM", "Wednesday: 10:00 AM \u2013 9:00 PM", "Thursday: 10:00 AM \u2013 9:00 PM", "Friday: 10:00 AM \u2013 9:00 PM", "Saturday: 10:00 AM \u2013 9:00 PM", "Sunday: 10:00 AM \u2013 8:00 PM"], "open_now": false, "periods": [{"close": {"day": 0, "time": "2000"}, "open": {"day": 0, "time": "1000"}}, {"close": {"day": 1, "time": "2100"}, "open": {"day": 1, "time": "1000"}}, {"close": {"day": 2, "time": "2100"}, "open": {"day": 2, "time": "1000"}}, {"close": {"day": 3, "time": "2100"}, "open": {"day": 3, "time": "1000"}}, {"close": {"day": 4, "time": "2100"}, "open": {"day": 4, "time": "1000"}}, {"close": {"day": 5, "time": "2100"}, "open": {"day": 5, "time": "1000"}}, {"close": {"day": 6, "time": "2100"}, "open": {"day": 6, "time": "1000"}}]}, "place_id": "ChIJo6ZHsMBZwokRBCS2f2XuMVU", "formatted_phone_number": "(917) 488-0044", "formatted_address": "88 10th Ave, New York, NY 10011, USA"}, {"rating": 3.8, "name": "New York & Company", "geometry": {"location": {"lat": 40.8370978, "lng": -73.8609542}, "viewport": {"northeast": {"lat": 40.8384279802915, "lng": -73.8595318197085}, "southwest": {"lat": 40.8357300197085, "lng": -73.8622297802915}}}, "opening_hours": {"weekday_text": ["Monday: 10:00 AM \u2013 8:00 PM", "Tuesday: 10:00 AM \u2013 8:00 PM", "Wednesday: 10:00 AM \u2013 8:00 PM", "Thursday: 10:00 AM \u2013 8:00 PM", "Friday: 10:00 AM \u2013 8:00 PM", "Saturday: 10:00 AM \u2013 8:00 PM", "Sunday: 11:00 AM \u2013 6:00 PM"], "open_now": false, "periods": [{"close": {"day": 0, "time": "1800"}, "open": {"day": 0, "time": "1100"}}, {"close": {"day": 1, "time": "2000"}, "open": {"day": 1, "time": "1000"}}, {"close": {"day": 2, "time": "2000"}, "open": {"day": 2, "time": "1000"}}, {"close": {"day": 3, "time": "2000"}, "open": {"day": 3, "time": "1000"}}, {"close": {"day": 4, "time": "2000"}, "open": {"day": 4, "time": "1000"}}, {"close": {"day": 5, "time": "2000"}, "open": {"day": 5, "time": "1000"}}, {"close": {"day": 6, "time": "2000"}, "open": {"day": 6, "time": "1000"}}]}, "place_id": "ChIJXxqwNr_0wokRo2CQ4vlQggI", "formatted_phone_number": "(718) 904-9282", "formatted_address": "1453 Metropolitan Ave #7, Bronx, NY 10462, USA"}, {"rating": 3.3, "name": "Toga Bike Shop", "geometry": {"location": {"lat": 40.7748037, "lng": -73.98785579999999}, "viewport": {"northeast": {"lat": 40.77619778029149, "lng": -73.98661356970848}, "southwest": {"lat": 40.7734998197085, "lng": -73.98931153029149}}}, "opening_hours": {"weekday_text": ["Monday: 11:00 AM \u2013 7:00 PM", "Tuesday: 11:00 AM \u2013 7:00 PM", "Wednesday: 11:00 AM \u2013 7:00 PM", "Thursday: 11:00 AM \u2013 8:00 PM", "Friday: 11:00 AM \u2013 7:00 PM", "Saturday: 10:00 AM \u2013 6:00 PM", "Sunday: 11:00 AM \u2013 6:00 PM"], "open_now": false, "periods": [{"close": {"day": 0, "time": "1800"}, "open": {"day": 0, "time": "1100"}}, {"close": {"day": 1, "time": "1900"}, "open": {"day": 1, "time": "1100"}}, {"close": {"day": 2, "time": "1900"}, "open": {"day": 2, "time": "1100"}}, {"close": {"day": 3, "time": "1900"}, "open": {"day": 3, "time": "1100"}}, {"close": {"day": 4, "time": "2000"}, "open": {"day": 4, "time": "1100"}}, {"close": {"day": 5, "time": "1900"}, "open": {"day": 5, "time": "1100"}}, {"close": {"day": 6, "time": "1800"}, "open": {"day": 6, "time": "1000"}}]}, "place_id": "ChIJQ9MPHF5YwokRNOs38qSxDM8", "formatted_phone_number": "(212) 799-9625", "formatted_address": "110 West End Ave, New York, NY 10023, USA"}, {"rating": 5, "name": "Dehati Mall", "geometry": {"location": {"lat": 40.7160722, "lng": -74.004954}, "viewport": {"northeast": {"lat": 40.7174211802915, "lng": -74.00360501970849}, "southwest": {"lat": 40.7147232197085, "lng": -74.00630298029151}}}, "opening_hours": {"weekday_text": ["Monday: Open 24 hours", "Tuesday: Open 24 hours", "Wednesday: Open 24 hours", "Thursday: Open 24 hours", "Friday: Open 24 hours", "Saturday: Open 24 hours", "Sunday: Open 24 hours"], "open_now": true, "periods": [{"open": {"day": 0, "time": "0000"}}]}, "place_id": "ChIJn2p1tSFawokRCCMGHsSwZY4", "formatted_address": "New York, NY 10007, USA"}, {"rating": 5, "name": "Tangchao Inc", "geometry": {"location": {"lat": 40.7138354, "lng": -73.99414030000001}, "viewport": {"northeast": {"lat": 40.71513598029151, "lng": -73.99278416970849}, "southwest": {"lat": 40.71243801970851, "lng": -73.99548213029149}}}, "opening_hours": {"weekday_text": ["Monday: 11:00 AM \u2013 7:00 PM", "Tuesday: 11:00 AM \u2013 7:00 PM", "Wednesday: 11:00 AM \u2013 7:00 PM", "Thursday: 11:00 AM \u2013 7:00 PM", "Friday: Closed", "Saturday: 11:00 AM \u2013 7:00 PM", "Sunday: 11:00 AM \u2013 7:00 PM"], "open_now": false, "periods": [{"close": {"day": 0, "time": "1900"}, "open": {"day": 0, "time": "1100"}}, {"close": {"day": 1, "time": "1900"}, "open": {"day": 1, "time": "1100"}}, {"close": {"day": 2, "time": "1900"}, "open": {"day": 2, "time": "1100"}}, {"close": {"day": 3, "time": "1900"}, "open": {"day": 3, "time": "1100"}}, {"close": {"day": 4, "time": "1900"}, "open": {"day": 4, "time": "1100"}}, {"close": {"day": 6, "time": "1900"}, "open": {"day": 6, "time": "1100"}}]}, "place_id": "ChIJq3ALmyhawokRUoR_1x4s2PY", "formatted_phone_number": "(917) 388-0528", "formatted_address": "114,, 88 E Broadway, New York, NY 10002, USA"}, {"rating": 4.5, "name": "Exit9 Gift Emporium NYC", "geometry": {"location": {"lat": 40.7241016, "lng": -73.9852646}, "viewport": {"northeast": {"lat": 40.72540223029149, "lng": -73.98379926970848}, "southwest": {"lat": 40.72270426970849, "lng": -73.98649723029149}}}, "opening_hours": {"weekday_text": ["Monday: 11:00 AM \u2013 7:30 PM", "Tuesday: 11:00 AM \u2013 7:30 PM", "Wednesday: 11:00 AM \u2013 7:30 PM", "Thursday: 11:00 AM \u2013 7:30 PM", "Friday: 11:00 AM \u2013 7:30 PM", "Saturday: 11:00 AM \u2013 8:00 PM", "Sunday: 12:00 \u2013 7:00 PM"], "open_now": false, "periods": [{"close": {"day": 0, "time": "1900"}, "open": {"day": 0, "time": "1200"}}, {"close": {"day": 1, "time": "1930"}, "open": {"day": 1, "time": "1100"}}, {"close": {"day": 2, "time": "1930"}, "open": {"day": 2, "time": "1100"}}, {"close": {"day": 3, "time": "1930"}, "open": {"day": 3, "time": "1100"}}, {"close": {"day": 4, "time": "1930"}, "open": {"day": 4, "time": "1100"}}, {"close": {"day": 5, "time": "1930"}, "open": {"day": 5, "time": "1100"}}, {"close": {"day": 6, "time": "2000"}, "open": {"day": 6, "time": "1100"}}]}, "place_id": "ChIJOzIewIJZwokRlex7MS_C-hQ", "formatted_phone_number": "(212) 228-0145", "formatted_address": "51 Avenue A, New York, NY 10009, USA"}, {"rating": 4.2, "name": "New York & Company", "geometry": {"location": {"lat": 40.6532669, "lng": -73.87187759999999}, "viewport": {"northeast": {"lat": 40.6546709802915, "lng": -73.87039906970848}, "southwest": {"lat": 40.65197301970851, "lng": -73.87309703029149}}}, "opening_hours": {"weekday_text": ["Monday: 10:00 AM \u2013 9:00 PM", "Tuesday: 10:00 AM \u2013 9:00 PM", "Wednesday: 10:00 AM \u2013 9:00 PM", "Thursday: 10:00 AM \u2013 9:00 PM", "Friday: 10:00 AM \u2013 9:00 PM", "Saturday: 10:00 AM \u2013 9:00 PM", "Sunday: 11:00 AM \u2013 7:00 PM"], "open_now": false, "periods": [{"close": {"day": 0, "time": "1900"}, "open": {"day": 0, "time": "1100"}}, {"close": {"day": 1, "time": "2100"}, "open": {"day": 1, "time": "1000"}}, {"close": {"day": 2, "time": "2100"}, "open": {"day": 2, "time": "1000"}}, {"close": {"day": 3, "time": "2100"}, "open": {"day": 3, "time": "1000"}}, {"close": {"day": 4, "time": "2100"}, "open": {"day": 4, "time": "1000"}}, {"close": {"day": 5, "time": "2100"}, "open": {"day": 5, "time": "1000"}}, {"close": {"day": 6, "time": "2100"}, "open": {"day": 6, "time": "1000"}}]}, "place_id": "ChIJeQYDhQ5dwokRyqawBQIG_TM", "formatted_phone_number": "(718) 647-2016", "formatted_address": "409 Gateway Dr, Brooklyn, NY 11239, USA"}, {"rating": 4.3, "name": "Macy's", "geometry": {"location": {"lat": 40.7508025, "lng": -73.98948349999999}, "viewport": {"northeast": {"lat": 40.75211118029149, "lng": -73.9879407697085}, "southwest": {"lat": 40.7494132197085, "lng": -73.99063873029151}}}, "opening_hours": {"weekday_text": ["Monday: 10:00 AM \u2013 10:00 PM", "Tuesday: 10:00 AM \u2013 10:00 PM", "Wednesday: 10:00 AM \u2013 10:00 PM", "Thursday: 10:00 AM \u2013 10:00 PM", "Friday: 10:00 AM \u2013 11:00 PM", "Saturday: 10:00 AM \u2013 11:00 PM", "Sunday: 10:00 AM \u2013 10:00 PM"], "open_now": false, "periods": [{"close": {"day": 0, "time": "2200"}, "open": {"day": 0, "time": "1000"}}, {"close": {"day": 1, "time": "2200"}, "open": {"day": 1, "time": "1000"}}, {"close": {"day": 2, "time": "2200"}, "open": {"day": 2, "time": "1000"}}, {"close": {"day": 3, "time": "2200"}, "open": {"day": 3, "time": "1000"}}, {"close": {"day": 4, "time": "2200"}, "open": {"day": 4, "time": "1000"}}, {"close": {"day": 5, "time": "2300"}, "open": {"day": 5, "time": "1000"}}, {"close": {"day": 6, "time": "2300"}, "open": {"day": 6, "time": "1000"}}]}, "place_id": "ChIJ3xjWra5ZwokRrwJ0KZ4yKNs", "formatted_phone_number": "(212) 695-4400", "formatted_address": "151 W 34th St, New York, NY 10001, USA"}, {"rating": 4.8, "name": "Strand Bookstore", "geometry": {"location": {"lat": 40.73331700000001, "lng": -73.9909639}, "viewport": {"northeast": {"lat": 40.7346659802915, "lng": -73.9896149197085}, "southwest": {"lat": 40.7319680197085, "lng": -73.99231288029151}}}, "opening_hours": {"weekday_text": ["Monday: 9:30 AM \u2013 10:30 PM", "Tuesday: 9:30 AM \u2013 10:30 PM", "Wednesday: 9:30 AM \u2013 10:30 PM", "Thursday: 9:30 AM \u2013 10:30 PM", "Friday: 9:30 AM \u2013 10:30 PM", "Saturday: 9:30 AM \u2013 10:30 PM", "Sunday: 11:00 AM \u2013 10:30 PM"], "open_now": false, "periods": [{"close": {"day": 0, "time": "2230"}, "open": {"day": 0, "time": "1100"}}, {"close": {"day": 1, "time": "2230"}, "open": {"day": 1, "time": "0930"}}, {"close": {"day": 2, "time": "2230"}, "open": {"day": 2, "time": "0930"}}, {"close": {"day": 3, "time": "2230"}, "open": {"day": 3, "time": "0930"}}, {"close": {"day": 4, "time": "2230"}, "open": {"day": 4, "time": "0930"}}, {"close": {"day": 5, "time": "2230"}, "open": {"day": 5, "time": "0930"}}, {"close": {"day": 6, "time": "2230"}, "open": {"day": 6, "time": "0930"}}]}, "place_id": "ChIJnSKGEJlZwokRQIpiCvzKzV4", "formatted_phone_number": "(212) 473-1452", "formatted_address": "828 Broadway, New York, NY 10003, USA"}, {"rating": 4.1, "name": "Fujifilm Wonder Photo Shop", "geometry": {"location": {"lat": 40.7411545, "lng": -73.9900821}, "viewport": {"northeast": {"lat": 40.7424713302915, "lng": -73.9886566197085}, "southwest": {"lat": 40.7397733697085, "lng": -73.9913545802915}}}, "opening_hours": {"weekday_text": ["Monday: 10:00 AM \u2013 7:00 PM", "Tuesday: 10:00 AM \u2013 7:00 PM", "Wednesday: 10:00 AM \u2013 7:00 PM", "Thursday: 10:00 AM \u2013 7:00 PM", "Friday: 10:00 AM \u2013 7:00 PM", "Saturday: 10:00 AM \u2013 7:00 PM", "Sunday: 12:00 \u2013 6:00 PM"], "open_now": false, "periods": [{"close": {"day": 0, "time": "1800"}, "open": {"day": 0, "time": "1200"}}, {"close": {"day": 1, "time": "1900"}, "open": {"day": 1, "time": "1000"}}, {"close": {"day": 2, "time": "1900"}, "open": {"day": 2, "time": "1000"}}, {"close": {"day": 3, "time": "1900"}, "open": {"day": 3, "time": "1000"}}, {"close": {"day": 4, "time": "1900"}, "open": {"day": 4, "time": "1000"}}, {"close": {"day": 5, "time": "1900"}, "open": {"day": 5, "time": "1000"}}, {"close": {"day": 6, "time": "1900"}, "open": {"day": 6, "time": "1000"}}]}, "place_id": "ChIJg1K29aNZwokRbrJKbWmtBeA", "formatted_phone_number": "(929) 239-4262", "formatted_address": "176 5th Ave, New York, NY 10010, USA"}, {"rating": 5, "name": "Ministry of Tomorrow - Vegan Luxury Designer Leather Hand Bags NY", "geometry": {"location": {"lat": 40.7110392, "lng": -74.01174840000002}, "viewport": {"northeast": {"lat": 40.7124445302915, "lng": -74.01068831970849}, "southwest": {"lat": 40.7097465697085, "lng": -74.0133862802915}}}, "opening_hours": {"weekday_text": ["Monday: 9:00 AM \u2013 7:30 PM", "Tuesday: 9:00 AM \u2013 7:30 PM", "Wednesday: 9:00 AM \u2013 7:30 PM", "Thursday: 9:00 AM \u2013 7:30 PM", "Friday: 9:00 AM \u2013 7:30 PM", "Saturday: 9:00 AM \u2013 7:30 PM", "Sunday: 9:00 AM \u2013 7:30 PM"], "open_now": false, "periods": [{"close": {"day": 0, "time": "1930"}, "open": {"day": 0, "time": "0900"}}, {"close": {"day": 1, "time": "1930"}, "open": {"day": 1, "time": "0900"}}, {"close": {"day": 2, "time": "1930"}, "open": {"day": 2, "time": "0900"}}, {"close": {"day": 3, "time": "1930"}, "open": {"day": 3, "time": "0900"}}, {"close": {"day": 4, "time": "1930"}, "open": {"day": 4, "time": "0900"}}, {"close": {"day": 5, "time": "1930"}, "open": {"day": 5, "time": "0900"}}, {"close": {"day": 6, "time": "1930"}, "open": {"day": 6, "time": "0900"}}]}, "place_id": "ChIJx_I4jRlawokRttXSQolQatk", "formatted_address": "185 Greenwich St, New York, NY 10007, USA"}, {"rating": 4.8, "name": "The Drama Book Shop Inc", "geometry": {"location": {"lat": 40.75545039999999, "lng": -73.9898286}, "viewport": {"northeast": {"lat": 40.75683833029149, "lng": -73.9884292197085}, "southwest": {"lat": 40.75414036970849, "lng": -73.9911271802915}}}, "opening_hours": {"weekday_text": ["Monday: 10:00 AM \u2013 7:00 PM", "Tuesday: 10:00 AM \u2013 7:00 PM", "Wednesday: 10:00 AM \u2013 7:00 PM", "Thursday: 10:00 AM \u2013 8:00 PM", "Friday: 10:00 AM \u2013 7:00 PM", "Saturday: 10:00 AM \u2013 7:00 PM", "Sunday: 12:00 \u2013 6:00 PM"], "open_now": false, "periods": [{"close": {"day": 0, "time": "1800"}, "open": {"day": 0, "time": "1200"}}, {"close": {"day": 1, "time": "1900"}, "open": {"day": 1, "time": "1000"}}, {"close": {"day": 2, "time": "1900"}, "open": {"day": 2, "time": "1000"}}, {"close": {"day": 3, "time": "1900"}, "open": {"day": 3, "time": "1000"}}, {"close": {"day": 4, "time": "2000"}, "open": {"day": 4, "time": "1000"}}, {"close": {"day": 5, "time": "1900"}, "open": {"day": 5, "time": "1000"}}, {"close": {"day": 6, "time": "1900"}, "open": {"day": 6, "time": "1000"}}]}, "place_id": "ChIJKwlmsKxZwokRfLTqxrJvDzY", "formatted_phone_number": "(212) 944-0595", "formatted_address": "250 W 40th St #1, New York, NY 10018, USA"}, {"rating": 4, "name": "Landmark Coffee Shop", "geometry": {"location": {"lat": 40.71995630000001, "lng": -73.99862499999999}, "viewport": {"northeast": {"lat": 40.72126338029151, "lng": -73.99731086970849}, "southwest": {"lat": 40.71856541970851, "lng": -74.00000883029149}}}, "opening_hours": {"weekday_text": ["Monday: 6:00 AM \u2013 6:00 PM", "Tuesday: 6:00 AM \u2013 6:00 PM", "Wednesday: 6:00 AM \u2013 6:00 PM", "Thursday: 6:00 AM \u2013 6:00 PM", "Friday: 6:00 AM \u2013 6:00 PM", "Saturday: 6:00 AM \u2013 6:00 PM", "Sunday: 6:00 AM \u2013 6:00 PM"], "open_now": false, "periods": [{"close": {"day": 0, "time": "1800"}, "open": {"day": 0, "time": "0600"}}, {"close": {"day": 1, "time": "1800"}, "open": {"day": 1, "time": "0600"}}, {"close": {"day": 2, "time": "1800"}, "open": {"day": 2, "time": "0600"}}, {"close": {"day": 3, "time": "1800"}, "open": {"day": 3, "time": "0600"}}, {"close": {"day": 4, "time": "1800"}, "open": {"day": 4, "time": "0600"}}, {"close": {"day": 5, "time": "1800"}, "open": {"day": 5, "time": "0600"}}, {"close": {"day": 6, "time": "1800"}, "open": {"day": 6, "time": "0600"}}]}, "place_id": "ChIJN66GpolZwokRAPJSwkC8FtE", "formatted_phone_number": "(212) 334-0040", "formatted_address": "158 Grand St, New York, NY 10013, USA"}, {"rating": 3.7, "name": "New York & Company", "geometry": {"location": {"lat": 40.762637, "lng": -73.9155396}, "viewport": {"northeast": {"lat": 40.76406678029149, "lng": -73.9143635197085}, "southwest": {"lat": 40.7613688197085, "lng": -73.91706148029151}}}, "opening_hours": {"weekday_text": ["Monday: 10:00 AM \u2013 8:00 PM", "Tuesday: 10:00 AM \u2013 8:00 PM", "Wednesday: 10:00 AM \u2013 8:00 PM", "Thursday: 10:00 AM \u2013 8:00 PM", "Friday: 10:00 AM \u2013 8:00 PM", "Saturday: 10:00 AM \u2013 8:00 PM", "Sunday: 11:00 AM \u2013 6:00 PM"], "open_now": false, "periods": [{"close": {"day": 0, "time": "1800"}, "open": {"day": 0, "time": "1100"}}, {"close": {"day": 1, "time": "2000"}, "open": {"day": 1, "time": "1000"}}, {"close": {"day": 2, "time": "2000"}, "open": {"day": 2, "time": "1000"}}, {"close": {"day": 3, "time": "2000"}, "open": {"day": 3, "time": "1000"}}, {"close": {"day": 4, "time": "2000"}, "open": {"day": 4, "time": "1000"}}, {"close": {"day": 5, "time": "2000"}, "open": {"day": 5, "time": "1000"}}, {"close": {"day": 6, "time": "2000"}, "open": {"day": 6, "time": "1000"}}]}, "place_id": "ChIJ6czb_T5fwokRUE1hE-pyv5Q", "formatted_phone_number": "(718) 204-0117", "formatted_address": "30-37 Steinway St #30, Astoria, NY 11103, USA"}, {"rating": 4.5, "name": "Disney Store", "geometry": {"location": {"lat": 40.75825709999999, "lng": -73.9850313}, "viewport": {"northeast": {"lat": 40.7596463802915, "lng": -73.9837957697085}, "southwest": {"lat": 40.75694841970851, "lng": -73.9864937302915}}}, "opening_hours": {"weekday_text": ["Monday: 9:00 AM \u2013 1:00 AM", "Tuesday: 9:00 AM \u2013 1:00 AM", "Wednesday: 9:00 AM \u2013 1:00 AM", "Thursday: 9:00 AM \u2013 1:00 AM", "Friday: 9:00 AM \u2013 1:00 AM", "Saturday: 9:00 AM \u2013 1:00 AM", "Sunday: 9:00 AM \u2013 1:00 AM"], "open_now": false, "periods": [{"close": {"day": 1, "time": "0100"}, "open": {"day": 0, "time": "0900"}}, {"close": {"day": 2, "time": "0100"}, "open": {"day": 1, "time": "0900"}}, {"close": {"day": 3, "time": "0100"}, "open": {"day": 2, "time": "0900"}}, {"close": {"day": 4, "time": "0100"}, "open": {"day": 3, "time": "0900"}}, {"close": {"day": 5, "time": "0100"}, "open": {"day": 4, "time": "0900"}}, {"close": {"day": 6, "time": "0100"}, "open": {"day": 5, "time": "0900"}}, {"close": {"day": 0, "time": "0100"}, "open": {"day": 6, "time": "0900"}}]}, "place_id": "ChIJf2_0qFVYwokRcbTtlS60Vqg", "formatted_phone_number": "(212) 626-2910", "formatted_address": "1540 Broadway, New York, NY 10036, USA"}]